i3grid/__init__.py
i3grid/__main__.py
i3grid/doc.py
i3grid/grid.py
i3grid/xrandr.py
i3_grid-0.2.3b3.dist-info/LICENSE
i3_grid-0.2.3b3.dist-info/METADATA
i3_grid-0.2.3b3.dist-info/WHEEL
i3_grid-0.2.3b3.dist-info/top_level.txt
i3_grid-0.2.3b3.dist-info/RECORD
