Metadata-Version: 2.1
Name: i3-grid
Version: 0.2.3b3
Summary: A i3wm grid controller for floating window automation.
Home-page: https://github.com/justahuman1/i3-grid
Author: Sai Valla
Author-email: saivdev@protonmail.com
License: UNKNOWN
Platform: UNKNOWN
Classifier: Programming Language :: Python :: 3
Classifier: License :: OSI Approved :: GNU General Public License v3 (GPLv3)
Classifier: Operating System :: POSIX :: Linux
Requires-Python: >=3.6
Requires-Dist: i3-py
